LICENSE
MANIFEST.in
README.md
setup.cfg
setup.py
docassemble.LAWVFamilyLaw.egg-info/PKG-INFO
docassemble.LAWVFamilyLaw.egg-info/SOURCES.txt
docassemble.LAWVFamilyLaw.egg-info/dependency_links.txt
docassemble.LAWVFamilyLaw.egg-info/not-zip-safe
docassemble.LAWVFamilyLaw.egg-info/requires.txt
docassemble.LAWVFamilyLaw.egg-info/top_level.txt
docassemble/LAWVFamilyLaw/__init__.py
docassemble/LAWVFamilyLaw/data/questions/family_law.yml
docassemble/LAWVFamilyLaw/data/sources/README.md
docassemble/LAWVFamilyLaw/data/static/README.md
docassemble/LAWVFamilyLaw/data/templates/README.md
docassemble/LAWVFamilyLaw/data/templates/fdvcsap.pdf
docassemble/LAWVFamilyLaw/data/templates/sca_fc_101.pdf
docassemble/LAWVFamilyLaw/data/templates/sca_fc_103.pdf
docassemble/LAWVFamilyLaw/data/templates/sca_fc_104.pdf
docassemble/LAWVFamilyLaw/data/templates/sca_fc_106.pdf
docassemble/LAWVFamilyLaw/data/templates/sca_fc_112.pdf
docassemble/LAWVFamilyLaw/data/templates/sca_fc_121.pdf
docassemble/LAWVFamilyLaw/data/templates/sca_fc_128.pdf
docassemble/LAWVFamilyLaw/data/templates/sca_fc_129.pdf
docassemble/LAWVFamilyLaw/data/templates/sca_fc_140.pdf