Metadata-Version: 2.2
Name: docassemble.LAWVFamilyLaw
Version: 0.1.8
Summary: A docassemble extension.
Home-page: https://docassemble.org
Author: System Administrator
Author-email: dhenry@lawv.net
License: The MIT License (MIT)
License-File: LICENSE
Requires-Dist: docassemble.LAWVCommon>=1.0.12
Requires-Dist: docassemble.LegalServerLink
Dynamic: author
Dynamic: author-email
Dynamic: description
Dynamic: description-content-type
Dynamic: home-page
Dynamic: license
Dynamic: requires-dist
Dynamic: summary
